m2x_mqtt/__init__.py
m2x_mqtt/api.py
m2x_mqtt/client.py
m2x_mqtt/utils.py
m2x_mqtt/v2/__init__.py
m2x_mqtt/v2/api.py
m2x_mqtt/v2/commands.py
m2x_mqtt/v2/devices.py
m2x_mqtt/v2/distributions.py
m2x_mqtt/v2/resource.py
m2x_mqtt/v2/streams.py
m2x_mqtt/v2/time.py
m2x_mqtt-0.4.0.dist-info/DESCRIPTION.rst
m2x_mqtt-0.4.0.dist-info/METADATA
m2x_mqtt-0.4.0.dist-info/RECORD
m2x_mqtt-0.4.0.dist-info/WHEEL
m2x_mqtt-0.4.0.dist-info/metadata.json
m2x_mqtt-0.4.0.dist-info/top_level.txt
