Metadata-Version: 2.0
Name: m2x-mqtt
Version: 0.4.0
Summary: M2X Python API client
Home-page: https://github.com/attm2x/m2x-python-mqtt
Author: Citrusbyte
Author-email: matia.saguirre@citrusbyte.com
License: BSD
Keywords: m2x,mqtt,api
Platform: UNKNOWN
Classifier: Development Status :: 4 - Beta
Classifier: Topic :: Internet
Classifier: License :: OSI Approved :: BSD License
Classifier: Intended Audience :: Developers
Classifier: Programming Language :: Python
Classifier: Programming Language :: Python :: 2.6
Classifier: Programming Language :: Python :: 2.7
Classifier: Programming Language :: Python :: 3
Classifier: Programming Language :: Python :: 3.3
Requires-Dist: iso8601 (==0.1.9)
Requires-Dist: paho-mqtt (==1.0)
